sharepointcli/__init__.py
sharepointcli/cli.py
sharepointcli/commons.py
sharepointcli/utils.py
sharepointcli-2.1.0.dist-info/LICENSE
sharepointcli-2.1.0.dist-info/METADATA
sharepointcli-2.1.0.dist-info/WHEEL
sharepointcli-2.1.0.dist-info/entry_points.txt
sharepointcli-2.1.0.dist-info/top_level.txt
sharepointcli-2.1.0.dist-info/zip-safe
sharepointcli-2.1.0.dist-info/RECORD
