Metadata-Version: 2.1
Name: sharepointcli
Version: 2.1.0
Summary: Command line interface for SharePoint
Home-page: http://github.com/andreax79/python-sharepoint-cli
Author: Andrea Bonomi
Author-email: andrea.bonomi@gmail.com
License: MIT
Keywords: sharepoint cli
Platform: UNKNOWN
Classifier: Operating System :: OS Independent
Classifier: Programming Language :: Python
Classifier: Topic :: Software Development :: Libraries :: Python Modules
Classifier: Programming Language :: Python :: 3.4
Classifier: Programming Language :: Python :: 3.5
Classifier: Programming Language :: Python :: 3.6
Classifier: Programming Language :: Python :: 3.7
Classifier: Programming Language :: Python :: 3.8
Classifier: Programming Language :: Python :: 3.9
Requires-Dist: O365
Requires-Dist: portalocker
Requires-Dist: requests
